LICENCE
README.md
setup.py
wiu/__init__.py
wiu/calculator.py
wiu/message.py
wiu.egg-info/PKG-INFO
wiu.egg-info/SOURCES.txt
wiu.egg-info/dependency_links.txt
wiu.egg-info/top_level.txt