Metadata-Version: 2.1
Name: wiu
Version: 0.0.6
Summary: A library made to practice and improve programming and english skills during our university.
Home-page: UNKNOWN
Author: Iuri Torres & João Witor
Author-email: iuri.t1000@gmail.com
License: MIT License
Keywords: wiu
Platform: UNKNOWN
License-File: LICENCE
